peg/__init__.py
peg/parser.py
mypeg-0.1.0.dist-info/METADATA
mypeg-0.1.0.dist-info/WHEEL
mypeg-0.1.0.dist-info/top_level.txt
mypeg-0.1.0.dist-info/RECORD
