Metadata-Version: 2.2
Name: mypeg
Version: 0.1.0
Summary: A simple PEG parser
Home-page: https://github.com/yourusername/mypeg
Author: Your Name
Author-email: Your Name <your.email@example.com>
Requires-Python: >=3.6
Requires-Dist: lark-parser
Dynamic: author
Dynamic: home-page
Dynamic: requires-python
